AutoRecorder/__init__.py
AutoRecorder/listener.py
robotframework_autorecorder-0.1.6.dist-info/LICENSE.txt
robotframework_autorecorder-0.1.6.dist-info/METADATA
robotframework_autorecorder-0.1.6.dist-info/WHEEL
robotframework_autorecorder-0.1.6.dist-info/top_level.txt
robotframework_autorecorder-0.1.6.dist-info/RECORD
