Metadata-Version: 2.1
Name: robotframework-autorecorder
Version: 0.1.6
Summary: Robot Framework AutoRecorder Library
Home-page: https://github.com/sebastianciupinski/robotframework-autorecorder
Author: Sebastian Ciupinski
Author-email: sebastian.ciupinski+robotframework-autorecorder@gmail.com
Classifier: Programming Language :: Python
Classifier: License :: OSI Approved :: MIT License
Classifier: Operating System :: OS Independent
License-File: LICENSE.txt
Requires-Dist: robotframework-screencaplibrary
